dissect/ffs/__init__.py
dissect/ffs/c_ffs.py
dissect/ffs/exceptions.py
dissect/ffs/ffs.py
dissect.ffs-3.10.dist-info/COPYRIGHT
dissect.ffs-3.10.dist-info/LICENSE
dissect.ffs-3.10.dist-info/METADATA
dissect.ffs-3.10.dist-info/WHEEL
dissect.ffs-3.10.dist-info/top_level.txt
dissect.ffs-3.10.dist-info/RECORD
